dagger/__init__.py
dagger/dagger.py
dagger_python3-1.3.1.dist-info/METADATA
dagger_python3-1.3.1.dist-info/RECORD
dagger_python3-1.3.1.dist-info/WHEEL
dagger_python3-1.3.1.dist-info/top_level.txt
