Metadata-Version: 2.1
Name: dagger-python3
Version: 1.3.1
Summary: File dependency graph evaluator.
Home-page: https://github.com/east301/dagger
Author: east301
Author-email: me@east301.net
License: GPL
Platform: UNKNOWN
Classifier: Development Status :: 5 - Production/Stable
Classifier: Intended Audience :: Developers
Classifier: License :: OSI Approved :: GNU General Public License (GPL)
Classifier: Natural Language :: English
Classifier: Operating System :: OS Independent
Classifier: Programming Language :: Python
Classifier: Topic :: Software Development :: Build Tools
